rlearn/__init__.py
rlearn/_version.py
rlearn/experiment/__init__.py
rlearn/experiment/_imbalanced.py
rlearn/experiment/tests/__init__.py
rlearn/experiment/tests/test_imbalanced.py
rlearn/model_selection/__init__.py
rlearn/model_selection/_search.py
rlearn/model_selection/tests/__init__.py
rlearn/model_selection/tests/test_search.py
rlearn/reporting/__init__.py
rlearn/reporting/_imbalanced/__init__.py
rlearn/reporting/_imbalanced/_datasets.py
rlearn/reporting/_imbalanced/_statistics.py
rlearn/reporting/_imbalanced/tests/__init__.py
rlearn/reporting/_imbalanced/tests/test_datasets.py
rlearn/reporting/_imbalanced/tests/test_statistics.py
rlearn/reporting/_search/__init__.py
rlearn/reporting/_search/_results.py
rlearn/reporting/_search/tests/__init__.py
rlearn/reporting/_search/tests/test_results.py
rlearn/utils/__init__.py
rlearn/utils/_validation.py
rlearn/utils/tests/__init__.py
rlearn/utils/tests/test_validation.py
research_learn-0.3.1.dist-info/LICENSE
research_learn-0.3.1.dist-info/METADATA
research_learn-0.3.1.dist-info/WHEEL
research_learn-0.3.1.dist-info/top_level.txt
research_learn-0.3.1.dist-info/RECORD
