Metadata-Version: 2.1
Name: research-learn
Version: 0.3.1
Summary: Toolbox for reproducible research in machine learning.
Home-page: https://github.com/AlgoWit/research-learn
Download-URL: https://github.com/AlgoWit/research-learn
Maintainer: G. Douzas
Maintainer-email: gdouzas@icloud.com
License: MIT
Platform: UNKNOWN
Classifier: Intended Audience :: Science/Research
Classifier: Intended Audience :: Developers
Classifier: License :: OSI Approved
Classifier: Programming Language :: Python
Classifier: Topic :: Software Development
Classifier: Topic :: Scientific/Engineering
Classifier: Operating System :: Microsoft :: Windows
Classifier: Operating System :: POSIX
Classifier: Operating System :: Unix
Classifier: Operating System :: MacOS
Classifier: Programming Language :: Python :: 3.8
Classifier: Programming Language :: Python :: 3.9
Classifier: Programming Language :: Python :: 3.10
License-File: LICENSE
Requires-Dist: scipy (>=0.17)
Requires-Dist: numpy (>=1.1)
Requires-Dist: pandas (>=0.23.0)
Requires-Dist: statsmodels (>=0.9.0)
Requires-Dist: scikit-learn (>=0.22)
Requires-Dist: imbalanced-learn (>=0.6.0)
Requires-Dist: rich (>=5.0.0)
Provides-Extra: docs
Requires-Dist: sphinx (==1.8.5) ; extra == 'docs'
Requires-Dist: sphinx-gallery ; extra == 'docs'
Requires-Dist: sphinx-rtd-theme ; extra == 'docs'
Requires-Dist: numpydoc ; extra == 'docs'
Requires-Dist: matplotlib ; extra == 'docs'
Provides-Extra: tests
Requires-Dist: pytest ; extra == 'tests'
Requires-Dist: pytest-cov ; extra == 'tests'
